Insomnia-0.0.0.dist-info/METADATA
Insomnia-0.0.0.dist-info/RECORD
Insomnia-0.0.0.dist-info/WHEEL
Insomnia-0.0.0.dist-info/top_level.txt
library/__init__.py
