Metadata-Version: 2.1
Name: Insomnia
Version: 0.0.0
Summary: To be updated
Home-page: UNKNOWN
Author: Ahura Jami
Author-email: UNKNOWN
License: UNKNOWN
Platform: UNKNOWN
Classifier: Programming Language :: Python :: 3
Classifier: License :: OSI Approved :: MIT License
Classifier: Operating System :: OS Independent
